generalized_additive_models/__init__.py
generalized_additive_models/distributions.py
generalized_additive_models/gam.py
generalized_additive_models/links.py
generalized_additive_models/optimizers.py
generalized_additive_models/penalties.py
generalized_additive_models/splinetransformer.py
generalized_additive_models/terms.py
generalized_additive_models/utils.py
generalized_additive_models/datasets/__init__.py
generalized_additive_models/datasets/bicycles.csv
generalized_additive_models/datasets/mcycle.csv
generalized_additive_models/datasets/powerlifters.csv
generalized_additive_models/datasets/salaries.csv
generalized_additive_models/datasets/test.csv
generalized_additive_models/inspection/__init__.py
generalized_additive_models/inspection/inspection.py
generalized_additive_models/inspection/partial_effect.py
generalized_additive_models/inspection/qq.py
generalized_additive_models/inspection/residual_histogram.py
generalized_additive_models/inspection/residual_scatter.py
generalized_additive_models/tests/benchmarking.py
generalized_additive_models/tests/test_against_other_software.py
generalized_additive_models/tests/test_datasets.py
generalized_additive_models/tests/test_distributions.py
generalized_additive_models/tests/test_gam.py
generalized_additive_models/tests/test_links.py
generalized_additive_models/tests/test_optimizers.py
generalized_additive_models/tests/test_terms.py
generalized_additive_models-0.4.3.dist-info/licenses/LICENSE.txt
generalized_additive_models-0.4.3.dist-info/METADATA
generalized_additive_models-0.4.3.dist-info/WHEEL
generalized_additive_models-0.4.3.dist-info/top_level.txt
generalized_additive_models-0.4.3.dist-info/RECORD
