Metadata-Version: 2.4
Name: generalized_additive_models
Version: 0.4.3
Summary: Generalized additive models in Python.
Author-email: tommyod <tommy.odland@gmail.com>
License: BSD 3-Clause License
Project-URL: Repository, https://github.com/tommyod/generalized-additive-models
Project-URL: Bug Reports, https://github.com/tommyod/generalized-additive-models/issues
Classifier: Development Status :: 3 - Alpha
Classifier: License :: OSI Approved :: BSD License
Classifier: Programming Language :: Python :: 3.9
Classifier: Programming Language :: Python :: 3.10
Classifier: Programming Language :: Python :: 3.11
Classifier: Programming Language :: Python :: 3.12
Classifier: Programming Language :: Python :: 3.13
Classifier: Topic :: Scientific/Engineering
Classifier: Operating System :: OS Independent
Classifier: Intended Audience :: Science/Research
License-File: LICENSE.txt
Requires-Dist: numpy
Requires-Dist: scipy
Requires-Dist: matplotlib
Requires-Dist: pandas
Requires-Dist: scikit-learn>=1.3.0
Requires-Dist: tabulate
Provides-Extra: lint
Requires-Dist: ruff; extra == "lint"
Requires-Dist: codespell; extra == "lint"
Provides-Extra: dev
Requires-Dist: pytest; extra == "dev"
Requires-Dist: pytest-cov; extra == "dev"
Requires-Dist: jupyter; extra == "dev"
Requires-Dist: setuptools; extra == "dev"
Requires-Dist: jupytext; extra == "dev"
Requires-Dist: pylint; extra == "dev"
Requires-Dist: twine; extra == "dev"
Requires-Dist: build; extra == "dev"
Provides-Extra: doc
Requires-Dist: sphinx; extra == "doc"
Requires-Dist: sphinxcontrib-napoleon; extra == "doc"
Requires-Dist: nbsphinx; extra == "doc"
Requires-Dist: ipython; extra == "doc"
Requires-Dist: sphinx_rtd_theme; extra == "doc"
Requires-Dist: pydata-sphinx-theme; extra == "doc"
Requires-Dist: numpydoc; extra == "doc"
Requires-Dist: Pillow; extra == "doc"
Requires-Dist: sphinx-gallery; extra == "doc"
Dynamic: license-file
